ramCOH/__init__.py
ramCOH/raman/__init__.py
ramCOH/raman/baseclass.py
ramCOH/raman/baseline_regions.py
ramCOH/raman/co2.py
ramCOH/raman/glass.py
ramCOH/raman/neon.py
ramCOH/signal_processing/__init__.py
ramCOH/signal_processing/curve_fitting.py
ramCOH/signal_processing/curves.py
ramCOH/signal_processing/deconvolution.py
ramCOH/signal_processing/functions.py
ramCOH/static/__init__.py
ramCOH/static/neon_emissionLines.csv
ramCOH-1.1.2.dist-info/LICENSE
ramCOH-1.1.2.dist-info/METADATA
ramCOH-1.1.2.dist-info/WHEEL
ramCOH-1.1.2.dist-info/top_level.txt
ramCOH-1.1.2.dist-info/RECORD
