Metadata-Version: 2.1
Name: ramCOH
Version: 1.1.2
Summary: Library for processing and peak fitting of Raman spectra, targeted at CO2 fluids and hydrous silicate glasses
Author: Thomas van Gerve
License: MIT License
Project-URL: Homepage, https://github.com/TDGerve/ramCOH
Classifier: Programming Language :: Python :: 3
Classifier: License :: OSI Approved :: MIT License
Classifier: Operating System :: OS Independent
Requires-Python: >=3.8
License-File: LICENSE
Requires-Dist: pandas
Requires-Dist: numpy
Requires-Dist: scipy
Requires-Dist: scikit-learn
Requires-Dist: csaps
